ai_workflows/__init__.py
ai_workflows/document_utilities.py
ai_workflows/llm_utilities.py
py_ai_workflows-0.31.0.dist-info/LICENSE
py_ai_workflows-0.31.0.dist-info/METADATA
py_ai_workflows-0.31.0.dist-info/WHEEL
py_ai_workflows-0.31.0.dist-info/top_level.txt
py_ai_workflows-0.31.0.dist-info/RECORD
