Metadata-Version: 2.1
Name: py-ai-workflows
Version: 0.31.0
Summary: A toolkit for AI workflows.
Home-page: https://github.com/higherbar-ai/ai-workflows
Author: Christopher Robert
Author-email: crobert@higherbar.ai
License: Apache 2.0
Project-URL: Documentation, https://ai-workflows.readthedocs.io/
Requires-Python: >=3.10
License-File: LICENSE
Requires-Dist: openai <2.0,>=1.99.0
Requires-Dist: anthropic[bedrock] ~=0.52.2
Requires-Dist: tiktoken
Requires-Dist: langsmith ~=0.3.43
Requires-Dist: tenacity
Requires-Dist: Pillow
Requires-Dist: jsonschema
Requires-Dist: colab-or-not ~=0.4.0
Requires-Dist: json-repair ==0.*
Provides-Extra: docs
Requires-Dist: unstructured[all-docs] ; extra == 'docs'
Requires-Dist: PyMuPDF ; extra == 'docs'
Requires-Dist: pymupdf4llm ; extra == 'docs'
Requires-Dist: openpyxl ; extra == 'docs'
Requires-Dist: nltk ==3.9.1 ; extra == 'docs'
Requires-Dist: beautifulsoup4 >=4.12.0 ; extra == 'docs'
Requires-Dist: markdown >=3.5.0 ; extra == 'docs'
Requires-Dist: docling <3.0,>=2.8.1 ; extra == 'docs'
